{
    "generic": [
        {
            "English": {
                "keywords": [
                    "kidnap",
                    "kidnapping",
                    "kidnapper",
                    "kidnapped"
                ],
                "mispellings": [
                    "troublesome",
                    "kidnapp",
                    "kiddnap",
                    "kidnape"
                ]
            },
            "Translation": {
                "lan": {
                    "keywords": [],
                    "mispellings": []
                }
            }
        },
        {
            "English": {
                "keywords": [
                    "death",
                    "dead",
                    "dying"
                ],
                "mispellings": [
                    "deeath",
                    "deat"
                ]
            },
            "Translation": {
                "lan": {
                    "keywords": [],
                    "mispellings": []
                }
            }
        },
        {
            "English": {
                "keywords": [
                    "illegal"
                ],
                "mispellings": [
                    "ilegal",
                    "ellegal",
                    "ileagaly"
                ]
            },
            "Translation": {
                "lan": {
                    "keywords": [],
                    "mispellings": []
                }
            }
        },
        {
            "English": {
                "keywords": [
                    "poison",
                    "poisoning",
                    "poisoned"
                ],
                "mispellings": [
                    "pesian",
                    "boisoned",
                    "poision",
                    "poisioning",
                    ""
                ]
            },
            "Translation": {
                "lan": {
                    "keywords": [],
                    "mispellings": []
                }
            }
        },
        {
            "English": {
                "keywords": [
                    "crisis",
                    "crises"
                ],
                "mispellings": [
                    "krisis",
                    "krises"
                ]
            },
            "Translation": {
                "lan": {
                    "keywords": [],
                    "mispellings": []
                }
            }
        },
        {
            "English": {
                "keywords": [
                    "trouble",
                    "troubling",
                    "troublesome",
                    "troubled"
                ],
                "mispellings": [
                    "troubl",
                    "trevel",
                    "trubl"
                ]
            },
            "Translation": {
                "lan": {
                    "keywords": [],
                    "mispellings": []
                }
            }
        },
        {
            "English": {
                "keywords": [
                    "victim",
                    "victimised"
                ],
                "mispellings": [
                    "victm",
                    "victimized",
                    "victem"
                ]
            },
            "Translation": {
                "lan": {
                    "keywords": [],
                    "mispellings": []
                }
            }
        },
        {
            "English": {
                "keywords": [
                    "emergency",
                    "911.0"
                ],
                "mispellings": [
                    "emergincy",
                    "emergincey",
                    "emergince",
                    "imerjensi"
                ]
            },
            "Translation": {
                "lan": {
                    "keywords": [],
                    "mispellings": []
                }
            }
        },
        {
            "English": {
                "keywords": [
                    "danger",
                    "dangerous",
                    "endangered"
                ],
                "mispellings": [
                    "dangeur",
                    "dangeer",
                    "dangre",
                    "dange"
                ]
            },
            "Translation": {
                "lan": {
                    "keywords": [],
                    "mispellings": []
                }
            }
        },
        {
            "English": {
                "keywords": [
                    "stalking",
                    "stalker",
                    "stalked"
                ],
                "mispellings": [
                    "staling",
                    "staking",
                    "stakling",
                    "stalkin",
                    "storking"
                ]
            },
            "Translation": {
                "lan": {
                    "keywords": [],
                    "mispellings": []
                }
            }
        },
        {
            "English": {
                "keywords": [
                    "follow",
                    "following",
                    "followed"
                ],
                "mispellings": [
                    "folow",
                    "folowed",
                    "followin",
                    "folowin"
                ]
            },
            "Translation": {
                "lan": {
                    "keywords": [],
                    "mispellings": []
                }
            }
        },
        {
            "English": {
                "keywords": [
                    "suffer",
                    "suffering",
                    "suffered",
                    "tortured"
                ],
                "mispellings": [
                    "sufer",
                    "sufering",
                    "sufered"
                ]
            },
            "Translation": {
                "lan": {
                    "keywords": [],
                    "mispellings": []
                }
            }
        },
        {
            "English": {
                "keywords": [
                    "hide",
                    "hiding",
                    "hid"
                ],
                "mispellings": [
                    "hidin",
                    "heed",
                    "haid"
                ]
            },
            "Translation": {
                "lan": {
                    "keywords": [],
                    "mispellings": []
                }
            }
        }
    ],
    "health": [
        {
            "English": {
                "keywords": [
                    "vomit",
                    "vomitted",
                    "vomitting"
                ],
                "mispellings": [
                    "yak",
                    "vomited",
                    "womit"
                ]
            },
            "Translation": {
                "lan": {
                    "keywords": [],
                    "mispellings": []
                }
            }
        },
        {
            "English": {
                "keywords": [
                    "puke",
                    "puking",
                    "puked"
                ],
                "mispellings": [
                    "pook",
                    "pukeing",
                    "pooking"
                ]
            },
            "Translation": {
                "lan": {
                    "keywords": [],
                    "mispellings": []
                }
            }
        },
        {
            "English": {
                "keywords": [
                    "disease",
                    "STD",
                    "diseases"
                ],
                "mispellings": [
                    "diseaze",
                    "dizeese",
                    "SDT"
                ]
            },
            "Translation": {
                "lan": {
                    "keywords": [],
                    "mispellings": []
                }
            }
        },
        {
            "English": {
                "keywords": [
                    "sick",
                    "sickness",
                    "sickly"
                ],
                "mispellings": [
                    "sik",
                    "seck",
                    "seek"
                ]
            },
            "Translation": {
                "lan": {
                    "keywords": [],
                    "mispellings": []
                }
            }
        },
        {
            "English": {
                "keywords": [
                    "ill",
                    "illness",
                    "illnesses"
                ],
                "mispellings": [
                    "illl",
                    "illniss",
                    "illnees"
                ]
            },
            "Translation": {
                "lan": {
                    "keywords": [],
                    "mispellings": []
                }
            }
        },
        {
            "English": {
                "keywords": [
                    "health",
                    "healthy"
                ],
                "mispellings": [
                    "haelth",
                    "healthy",
                    "helath"
                ]
            },
            "Translation": {
                "lan": {
                    "keywords": [],
                    "mispellings": []
                }
            }
        },
        {
            "English": {
                "keywords": [
                    "hospital",
                    "clinic"
                ],
                "mispellings": [
                    "hopital",
                    "hopsital",
                    "celinic"
                ]
            },
            "Translation": {
                "lan": {
                    "keywords": [],
                    "mispellings": []
                }
            }
        },
        {
            "English": {
                "keywords": [
                    "miscarriage",
                    "miscarry"
                ],
                "mispellings": [
                    "miscariage",
                    "miscarig"
                ]
            },
            "Translation": {
                "lan": {
                    "keywords": [],
                    "mispellings": []
                }
            }
        },
        {
            "English": {
                "keywords": [
                    "pregnant",
                    "pregnancy",
                    "expecting"
                ],
                "mispellings": [
                    "pegant",
                    "preganci",
                    "prengant"
                ]
            },
            "Translation": {
                "lan": {
                    "keywords": [],
                    "mispellings": []
                }
            }
        },
        {
            "English": {
                "keywords": [
                    "abortion",
                    "abort",
                    "aborted",
                    "aborting"
                ],
                "mispellings": [
                    "abbortion",
                    "obortion"
                ]
            },
            "Translation": {
                "lan": {
                    "keywords": [],
                    "mispellings": []
                }
            }
        },
        {
            "English": {
                "keywords": [
                    "COVID",
                    "COVID19"
                ],
                "mispellings": []
            },
            "Translation": {
                "lan": {
                    "keywords": [],
                    "mispellings": []
                }
            }
        }
    ],
    "mental_health": [
        {
            "English": {
                "keywords": [
                    "anxiety",
                    "anxious",
                    "anxiousness"
                ],
                "mispellings": [
                    "angziaty",
                    "anxieti",
                    "anxeity"
                ]
            },
            "Translation": {
                "lan": {
                    "keywords": [],
                    "mispellings": []
                }
            }
        },
        {
            "English": {
                "keywords": [
                    "depression",
                    "depressive",
                    "depressed"
                ],
                "mispellings": [
                    "despression",
                    "despressive",
                    "despressed"
                ]
            },
            "Translation": {
                "lan": {
                    "keywords": [],
                    "mispellings": []
                }
            }
        },
        {
            "English": {
                "keywords": [
                    "disorder",
                    "disorders"
                ],
                "mispellings": [
                    "dizorder",
                    "dissorder",
                    "isorder"
                ]
            },
            "Translation": {
                "lan": {
                    "keywords": [],
                    "mispellings": []
                }
            }
        },
        {
            "English": {
                "keywords": [
                    "therapy"
                ],
                "mispellings": [
                    "therapi",
                    "therepy",
                    "therepi"
                ]
            },
            "Translation": {
                "lan": {
                    "keywords": [],
                    "mispellings": []
                }
            }
        },
        {
            "English": {
                "keywords": [
                    "psychologist"
                ],
                "mispellings": [
                    "sychology",
                    "psichology"
                ]
            },
            "Translation": {
                "lan": {
                    "keywords": [],
                    "mispellings": []
                }
            }
        },
        {
            "English": {
                "keywords": [
                    "suicide",
                    "suicidal",
                    "suicides"
                ],
                "mispellings": [
                    "suicido",
                    "suiced"
                ]
            },
            "Translation": {
                "lan": {
                    "keywords": [],
                    "mispellings": []
                }
            }
        },
        {
            "English": {
                "keywords": [
                    "stress",
                    "stressed"
                ],
                "mispellings": [
                    "stresss",
                    "strees",
                    "srtess",
                    "stres"
                ]
            },
            "Translation": {
                "lan": {
                    "keywords": [],
                    "mispellings": []
                }
            }
        },
        {
            "English": {
                "keywords": [
                    "distress",
                    "distressed"
                ],
                "mispellings": [
                    "destressed",
                    "destresss",
                    "detresse",
                    "detresse"
                ]
            },
            "Translation": {
                "lan": {
                    "keywords": [],
                    "mispellings": []
                }
            }
        },
        {
            "English": {
                "keywords": [
                    "sad",
                    "saddened"
                ],
                "mispellings": [
                    "sadd",
                    "saddenned",
                    "sadend"
                ]
            },
            "Translation": {
                "lan": {
                    "keywords": [],
                    "mispellings": []
                }
            }
        },
        {
            "English": {
                "keywords": [
                    "scare",
                    "scared"
                ],
                "mispellings": [
                    "csared",
                    "csare"
                ]
            },
            "Translation": {
                "lan": {
                    "keywords": [],
                    "mispellings": []
                }
            }
        },
        {
            "English": {
                "keywords": [
                    "afraid"
                ],
                "mispellings": [
                    "afaid"
                ]
            },
            "Translation": {
                "lan": {
                    "keywords": [],
                    "mispellings": []
                }
            }
        },
        {
            "English": {
                "keywords": [
                    "worried"
                ],
                "mispellings": [
                    "woried"
                ]
            },
            "Translation": {
                "lan": {
                    "keywords": [],
                    "mispellings": []
                }
            }
        },
        {
            "English": {
                "keywords": [
                    "fear",
                    "frighten"
                ],
                "mispellings": [
                    "fer",
                    "feer"
                ]
            },
            "Translation": {
                "lan": {
                    "keywords": [],
                    "mispellings": []
                }
            }
        },
        {
            "English": {
                "keywords": [
                    "panic",
                    "panicking",
                    "panicked"
                ],
                "mispellings": [
                    "panik",
                    "paniked",
                    "paniking"
                ]
            },
            "Translation": {
                "lan": {
                    "keywords": [],
                    "mispellings": []
                }
            }
        },
        {
            "English": {
                "keywords": [
                    "mad"
                ],
                "mispellings": [
                    "md",
                    "made"
                ]
            },
            "Translation": {
                "lan": {
                    "keywords": [],
                    "mispellings": []
                }
            }
        },
        {
            "English": {
                "keywords": [
                    "grief"
                ],
                "mispellings": [
                    "greif",
                    "griev"
                ]
            },
            "Translation": {
                "lan": {
                    "keywords": [],
                    "mispellings": []
                }
            }
        }
    ],
    "natural_disasters": [
        {
            "English": {
                "keywords": [
                    "fire",
                    "wildfire",
                    "blaze",
                    "burnt"
                ],
                "mispellings": [
                    "blaz",
                    "brun",
                    "fier",
                    "fir"
                ]
            },
            "Translation": {
                "lan": {
                    "keywords": [],
                    "mispellings": []
                }
            }
        },
        {
            "English": {
                "keywords": [
                    "earthquake",
                    "Landslide",
                    "collapse"
                ],
                "mispellings": [
                    "shake",
                    "irthquake",
                    "earthquak",
                    "fall"
                ]
            },
            "Translation": {
                "lan": {
                    "keywords": [],
                    "mispellings": []
                }
            }
        },
        {
            "English": {
                "keywords": [
                    "flood",
                    "flooded",
                    "flooding"
                ],
                "mispellings": [
                    "flud",
                    "flod",
                    "munson",
                    "monson",
                    "monsun"
                ]
            },
            "Translation": {
                "lan": {
                    "keywords": [],
                    "mispellings": []
                }
            }
        },
        {
            "English": {
                "keywords": [
                    "smoke",
                    "smoked",
                    "smoking"
                ],
                "mispellings": [
                    "smooke",
                    "smok"
                ]
            },
            "Translation": {
                "lan": {
                    "keywords": [],
                    "mispellings": []
                }
            }
        },
        {
            "English": {
                "keywords": [
                    "typhoon",
                    "hurricane",
                    "tornado",
                    "cyclone"
                ],
                "mispellings": [
                    "storm",
                    "rain",
                    "water",
                    "stormy"
                ]
            },
            "Translation": {
                "lan": {
                    "keywords": [],
                    "mispellings": []
                }
            }
        },
        {
            "English": {
                "keywords": [
                    "droughts",
                    "dry",
                    "aridity"
                ],
                "mispellings": [
                    "dri"
                ]
            },
            "Translation": {
                "lan": {
                    "keywords": [],
                    "mispellings": []
                }
            }
        },
        {
            "English": {
                "keywords": [
                    "volcanic eruption",
                    "volcano"
                ],
                "mispellings": [
                    "fire",
                    "hot"
                ]
            },
            "Translation": {
                "lan": {
                    "keywords": [],
                    "mispellings": []
                }
            }
        },
        {
            "English": {
                "keywords": [
                    "wind",
                    "blast"
                ],
                "mispellings": [
                    "air"
                ]
            },
            "Translation": {
                "lan": {
                    "keywords": [],
                    "mispellings": []
                }
            }
        }
    ],
    "menu": [
        {
            "English": {
                "keywords": [
                    "MENU",
                    "Main Menu"
                ],
                "mispellings": [
                    "Menue",
                    "meny",
                    "manu",
                    "meun"
                ]
            },
            "Translation": {
                "lan": {
                    "keywords": [],
                    "mispellings": []
                }
            }
        }
    ],
    "help": [
        {
            "English": {
                "keywords": [
                    "HELP"
                ],
                "mispellings": [
                    "halp",
                    "hep",
                    "hlep",
                    "hellp"
                ]
            },
            "Translation": {
                "lan": {
                    "keywords": [],
                    "mispellings": []
                }
            }
        }
    ],
    "pause": [
        {
            "English": {
                "keywords": [
                    "PAUSE"
                ],
                "mispellings": [
                    "Puase",
                    "Paws",
                    "Paus"
                ]
            },
            "Translation": {
                "lan": {
                    "keywords": [],
                    "mispellings": []
                }
            }
        }
    ],
    "start": [
        {
            "English": {
                "keywords": [
                    "test"
                ],
                "mispellings": []
            },
            "Translation": {
                "lan": {
                    "keywords": [
                        "test"
                    ],
                    "mispellings": []
                }
            }
        }
    ],
    "stop": [
        {
            "English": {
                "keywords": [
                    "stop"
                ],
                "mispellings": [
                    "spot",
                    "sotp",
                    "atop"
                ]
            },
            "Translation": {
                "lan": {
                    "keywords": [],
                    "mispellings": []
                }
            }
        }
    ],
    "play": [
        {
            "English": {
                "keywords": [
                    "PLAY"
                ],
                "mispellings": [
                    "paly",
                    "pla",
                    "pley",
                    "plaay"
                ]
            },
            "Translation": {
                "lan": {
                    "keywords": [],
                    "mispellings": []
                }
            }
        }
    ]
}